{"errors":[],"warnings":[],"namedChunkGroups":{"app":{"chunks":[9,1,0,2],"assets":["webpack-runtime-fa90db35195bfeff913f.js","webpack-runtime-fa90db35195bfeff913f.js.map","styles.3827050ba5f84f4d80f5.css","styles-4416f944b41d85fc67a6.js","styles-4416f944b41d85fc67a6.js.map","commons-d7fae86b5b9529f04cca.js","commons-d7fae86b5b9529f04cca.js.map","app-034f673cd0b5b48790fa.js","app-034f673cd0b5b48790fa.js.map"],"children":{},"childAssets":{}},"component---src-components-post-js":{"chunks":[1,0,3],"assets":["styles.3827050ba5f84f4d80f5.css","styles-4416f944b41d85fc67a6.js","styles-4416f944b41d85fc67a6.js.map","commons-d7fae86b5b9529f04cca.js","commons-d7fae86b5b9529f04cca.js.map","component---src-components-post-js-45fefff39ab66490bc41.js","component---src-components-post-js-45fefff39ab66490bc41.js.map"],"children":{},"childAssets":{}},"component---src-pages-404-js":{"chunks":[1,0,4],"assets":["styles.3827050ba5f84f4d80f5.css","styles-4416f944b41d85fc67a6.js","styles-4416f944b41d85fc67a6.js.map","commons-d7fae86b5b9529f04cca.js","commons-d7fae86b5b9529f04cca.js.map","component---src-pages-404-js-f1156d41b696ee7553d7.js","component---src-pages-404-js-f1156d41b696ee7553d7.js.map"],"children":{},"childAssets":{}},"component---src-pages-about-js":{"chunks":[1,0,5],"assets":["styles.3827050ba5f84f4d80f5.css","styles-4416f944b41d85fc67a6.js","styles-4416f944b41d85fc67a6.js.map","commons-d7fae86b5b9529f04cca.js","commons-d7fae86b5b9529f04cca.js.map","component---src-pages-about-js-f155fe575e1513534068.js","component---src-pages-about-js-f155fe575e1513534068.js.map"],"children":{},"childAssets":{}},"component---src-pages-index-js":{"chunks":[1,0,6],"assets":["styles.3827050ba5f84f4d80f5.css","styles-4416f944b41d85fc67a6.js","styles-4416f944b41d85fc67a6.js.map","commons-d7fae86b5b9529f04cca.js","commons-d7fae86b5b9529f04cca.js.map","component---src-pages-index-js-1cfad00dcb4ebb9a7a5e.js","component---src-pages-index-js-1cfad00dcb4ebb9a7a5e.js.map"],"children":{},"childAssets":{}},"component---src-pages-projects-js":{"chunks":[1,0,7],"assets":["styles.3827050ba5f84f4d80f5.css","styles-4416f944b41d85fc67a6.js","styles-4416f944b41d85fc67a6.js.map","commons-d7fae86b5b9529f04cca.js","commons-d7fae86b5b9529f04cca.js.map","component---src-pages-projects-js-edc95acce9d249c2fd6f.js","component---src-pages-projects-js-edc95acce9d249c2fd6f.js.map"],"children":{},"childAssets":{}},"component---src-pages-resume-js":{"chunks":[1,0,8],"assets":["styles.3827050ba5f84f4d80f5.css","styles-4416f944b41d85fc67a6.js","styles-4416f944b41d85fc67a6.js.map","commons-d7fae86b5b9529f04cca.js","commons-d7fae86b5b9529f04cca.js.map","component---src-pages-resume-js-b905fad51c3ea36891c5.js","component---src-pages-resume-js-b905fad51c3ea36891c5.js.map"],"children":{},"childAssets":{}}},"assetsByChunkName":{"app":["webpack-runtime-fa90db35195bfeff913f.js","styles.3827050ba5f84f4d80f5.css","styles-4416f944b41d85fc67a6.js","commons-d7fae86b5b9529f04cca.js","app-034f673cd0b5b48790fa.js"],"component---src-components-post-js":["styles.3827050ba5f84f4d80f5.css","styles-4416f944b41d85fc67a6.js","commons-d7fae86b5b9529f04cca.js","component---src-components-post-js-45fefff39ab66490bc41.js"],"component---src-pages-404-js":["styles.3827050ba5f84f4d80f5.css","styles-4416f944b41d85fc67a6.js","commons-d7fae86b5b9529f04cca.js","component---src-pages-404-js-f1156d41b696ee7553d7.js"],"component---src-pages-about-js":["styles.3827050ba5f84f4d80f5.css","styles-4416f944b41d85fc67a6.js","commons-d7fae86b5b9529f04cca.js","component---src-pages-about-js-f155fe575e1513534068.js"],"component---src-pages-index-js":["styles.3827050ba5f84f4d80f5.css","styles-4416f944b41d85fc67a6.js","commons-d7fae86b5b9529f04cca.js","component---src-pages-index-js-1cfad00dcb4ebb9a7a5e.js"],"component---src-pages-projects-js":["styles.3827050ba5f84f4d80f5.css","styles-4416f944b41d85fc67a6.js","commons-d7fae86b5b9529f04cca.js","component---src-pages-projects-js-edc95acce9d249c2fd6f.js"],"component---src-pages-resume-js":["styles.3827050ba5f84f4d80f5.css","styles-4416f944b41d85fc67a6.js","commons-d7fae86b5b9529f04cca.js","component---src-pages-resume-js-b905fad51c3ea36891c5.js"]}}